deadline/unreal_adaptor/__init__.py
deadline/unreal_adaptor/_version.py
deadline/unreal_adaptor/UnrealAdaptor/__init__.py
deadline/unreal_adaptor/UnrealAdaptor/__main__.py
deadline/unreal_adaptor/UnrealAdaptor/adaptor.py
deadline/unreal_adaptor/UnrealAdaptor/common.py
deadline/unreal_adaptor/UnrealAdaptor/py.typed
deadline/unreal_adaptor/UnrealAdaptor/schemas/init_data.schema.json
deadline/unreal_adaptor/UnrealAdaptor/schemas/run_data.schema.json
deadline/unreal_adaptor/UnrealClient/__init__.py
deadline/unreal_adaptor/UnrealClient/py.typed
deadline/unreal_adaptor/UnrealClient/unreal_client.py
deadline/unreal_adaptor/UnrealClient/step_handlers/__init__.py
deadline/unreal_adaptor/UnrealClient/step_handlers/base_step_handler.py
deadline/unreal_adaptor/UnrealClient/step_handlers/unreal_custom_step_handler.py
deadline/unreal_adaptor/UnrealClient/step_handlers/unreal_render_step_handler.py
deadline/unreal_cmd_utils/__init__.py
deadline/unreal_cmd_utils/_version.py
deadline/unreal_cmd_utils/cmd_utils.py
deadline/unreal_logger/__init__.py
deadline/unreal_logger/_version.py
deadline/unreal_logger/handlers.py
deadline/unreal_logger/logger.py
deadline/unreal_perforce_utils/__init__.py
deadline/unreal_perforce_utils/_version.py
deadline/unreal_perforce_utils/app.py
deadline/unreal_perforce_utils/cli.py
deadline/unreal_perforce_utils/exceptions.py
deadline/unreal_perforce_utils/perforce.py
deadline/unreal_perforce_utils/secret_manager.py
deadline/unreal_perforce_utils/unreal_source_control.py
deadline/unreal_submitter/__init__.py
deadline/unreal_submitter/_version.py
deadline/unreal_submitter/common.py
deadline/unreal_submitter/exceptions.py
deadline/unreal_submitter/settings.py
deadline/unreal_submitter/submitter.py
deadline/unreal_submitter/unreal_dependency_collector.py
deadline/unreal_submitter/unreal_open_job/__init__.py
deadline/unreal_submitter/unreal_open_job/unreal_open_job.py
deadline/unreal_submitter/unreal_open_job/unreal_open_job_entity.py
deadline_cloud_for_unreal_engine-0.6.4.dist-info/METADATA
deadline_cloud_for_unreal_engine-0.6.4.dist-info/WHEEL
deadline_cloud_for_unreal_engine-0.6.4.dist-info/entry_points.txt
deadline_cloud_for_unreal_engine-0.6.4.dist-info/licenses/LICENSE
deadline_cloud_for_unreal_engine-0.6.4.dist-info/licenses/NOTICE
deadline_cloud_for_unreal_engine-0.6.4.dist-info/RECORD
