Metadata-Version: 2.4
Name: deadline-cloud-for-unreal-engine
Version: 0.6.4
Summary: AWS Deadline Cloud for Unreal Engine
Project-URL: Homepage, https://github.com/aws-deadline/deadline-cloud-for-unreal-engine
Project-URL: Source, https://github.com/aws-deadline/deadline-cloud-for-unreal-engine
Author: Amazon Web Services
License-Expression: Apache-2.0
License-File: LICENSE
License-File: NOTICE
Classifier: Development Status :: 5 - Production/Stable
Classifier: Intended Audience :: Developers
Classifier: Intended Audience :: End Users/Desktop
Classifier: License :: OSI Approved :: Apache Software License
Classifier: Operating System :: Microsoft :: Windows
Classifier: Programming Language :: Python
Classifier: Programming Language :: Python :: 3 :: Only
Classifier: Programming Language :: Python :: 3.9
Classifier: Programming Language :: Python :: 3.10
Classifier: Programming Language :: Python :: 3.11
Classifier: Programming Language :: Python :: 3.12
Requires-Python: >=3.9
Requires-Dist: deadline<0.53,>=0.51
Requires-Dist: openjd-adaptor-runtime<0.10,>=0.8.1
Requires-Dist: openjd-model<0.9,>=0.8.1
Requires-Dist: p4python==2025.1.2767466
Requires-Dist: psutil>=5.9.0
